tomlconfig/__init__.py
tomlconfig/base.py
tomlconfig/core.py
tomlconfig-1.2.1.dist-info/LICENSE
tomlconfig-1.2.1.dist-info/METADATA
tomlconfig-1.2.1.dist-info/WHEEL
tomlconfig-1.2.1.dist-info/top_level.txt
tomlconfig-1.2.1.dist-info/RECORD
