Metadata-Version: 2.1
Name: tomlconfig
Version: 1.2.1
Summary: UNKNOWN
Home-page: https://github.com/hustlei/tomlconfig
Author: lileilei
Author-email: hustlei@sina.cn
License: UNKNOWN
Project-URL: Source Code, https://github.com/hustlei/tomlconfig
Keywords: toml config parser
Platform: UNKNOWN
Classifier: License :: OSI Approved :: GNU Lesser General Public License v3 or later (LGPLv3+)
Classifier: Programming Language :: Python :: 3
Classifier: Operating System :: OS Independent
Requires-Dist: toml
